relationalize/__init__.py
relationalize/py.typed
relationalize/relationalize.py
relationalize/schema.py
relationalize/sql_dialects.py
relationalize/utils.py
relationalize-0.1.7.dist-info/LICENSE.md
relationalize-0.1.7.dist-info/METADATA
relationalize-0.1.7.dist-info/WHEEL
relationalize-0.1.7.dist-info/top_level.txt
relationalize-0.1.7.dist-info/RECORD
