Metadata-Version: 2.1
Name: relationalize
Version: 0.1.7
Summary: A utility for converting/transporting arbitrary JSON data collections into a relational database
Home-page: https://github.com/tulip/relationalize
Author: Henry Jones
Author-email: Henry Jones <henry.jones@tulip.co>
Keywords: tulip,relationalize,json,relational,array
Classifier: Programming Language :: Python :: 3
Classifier: Operating System :: OS Independent
Requires-Python: >=3.6
License-File: LICENSE.md
